<?xml version="1.0" encoding="UTF-8"?>
<metadata xml:lang="ru"><Esri><CreaDate>20190520</CreaDate><CreaTime>12341100</CreaTime><ArcGISFormat>1.0</ArcGISFormat><SyncOnce>TRUE</SyncOnce><DataProperties><lineage><Process ToolSource="c:\program files (x86)\arcgis\desktop10.4\ArcToolbox\Toolboxes\Spatial Analyst Tools.tbx\Contour" Date="20190520" Time="123411">Contour foxlake F:\Demidov\PythEveryone\PyCharmProject\Lesson1\foxlake_Foxlake2.shp 25 0 1</Process><Process ToolSource="F:\Demidov\PythEveryone\PyCharmProject\Lesson1\Precip2008\Practice.tbx\Foxlake" Date="20190520" Time="123411">Foxlake foxlake F:\Demidov\PythEveryone\PyCharmProject\Lesson1\foxlake_Foxlake2.shp</Process></lineage></DataProperties></Esri></metadata>
